eth_abi/__init__.py
eth_abi/abi.py
eth_abi/base.py
eth_abi/codec.py
eth_abi/constants.py
eth_abi/decoding.py
eth_abi/encoding.py
eth_abi/exceptions.py
eth_abi/grammar.py
eth_abi/packed.py
eth_abi/py.typed
eth_abi/registry.py
eth_abi/tools/__init__.py
eth_abi/tools/_strategies.py
eth_abi/utils/__init__.py
eth_abi/utils/numeric.py
eth_abi/utils/padding.py
eth_abi/utils/string.py
eth_abi/utils/validation.py
eth_abi-5.1.0.dist-info/LICENSE
eth_abi-5.1.0.dist-info/METADATA
eth_abi-5.1.0.dist-info/WHEEL
eth_abi-5.1.0.dist-info/top_level.txt
eth_abi-5.1.0.dist-info/RECORD
